GDPRUtils/keyvault.py
GDPRUtils-0.0.1.dist-info/LICENSE.txt
GDPRUtils-0.0.1.dist-info/METADATA
GDPRUtils-0.0.1.dist-info/WHEEL
GDPRUtils-0.0.1.dist-info/top_level.txt
GDPRUtils-0.0.1.dist-info/RECORD
