Metadata-Version: 2.1
Name: GDPRUtils
Version: 0.0.1
Summary: Package publication test
Author-email: Mariano Mancini <qhawaq@gmail.com>
License: Copyright (c) 2018 The Python Packaging Authority
Project-URL: Homepage, https://github.com/pypa/sampleproject
Project-URL: Issues, https://github.com/pypa/sampleproject/issues
Keywords: GDPR
Classifier: Development Status :: 3 - Alpha
Classifier: Programming Language :: Python :: 3
Classifier: License :: OSI Approved :: MIT License
Classifier: Operating System :: OS Independent
Requires-Python: >=3.10
License-File: LICENSE.txt
Requires-Dist: yaml
Requires-Dist: json
Requires-Dist: requests
Requires-Dist: pydantic
Requires-Dist: criptography
Requires-Dist: fastapi
